haystack_integrations/components/connectors/py.typed
haystack_integrations/components/connectors/github/__init__.py
haystack_integrations/components/connectors/github/file_editor.py
haystack_integrations/components/connectors/github/issue_commenter.py
haystack_integrations/components/connectors/github/issue_viewer.py
haystack_integrations/components/connectors/github/pr_creator.py
haystack_integrations/components/connectors/github/repo_forker.py
haystack_integrations/components/connectors/github/repo_viewer.py
haystack_integrations/prompts/py.typed
haystack_integrations/prompts/github/__init__.py
haystack_integrations/prompts/github/context_prompt.py
haystack_integrations/prompts/github/file_editor_prompt.py
haystack_integrations/prompts/github/issue_commenter_prompt.py
haystack_integrations/prompts/github/issue_viewer_prompt.py
haystack_integrations/prompts/github/pr_creator_prompt.py
haystack_integrations/prompts/github/repo_forker_prompt.py
haystack_integrations/prompts/github/repo_viewer_prompt.py
haystack_integrations/prompts/github/system_prompt.py
haystack_integrations/tools/py.typed
haystack_integrations/tools/github/__init__.py
haystack_integrations/tools/github/file_editor_tool.py
haystack_integrations/tools/github/issue_commenter_tool.py
haystack_integrations/tools/github/issue_viewer_tool.py
haystack_integrations/tools/github/pr_creator_tool.py
haystack_integrations/tools/github/repo_forker_tool.py
haystack_integrations/tools/github/repo_viewer_tool.py
haystack_integrations/tools/github/utils.py
github_haystack-1.2.1.dist-info/METADATA
github_haystack-1.2.1.dist-info/WHEEL
github_haystack-1.2.1.dist-info/licenses/LICENSE.txt
github_haystack-1.2.1.dist-info/RECORD
