Metadata-Version: 2.4
Name: github-haystack
Version: 1.2.1
Summary: Haystack components for interacting with GitHub repositories
Project-URL: Source, https://github.com/deepset-ai/haystack-core-integrations/github
Project-URL: Documentation, https://github.com/deepset-ai/haystack-core-integrations/blob/main/integrations/github/README.md
Project-URL: Issues, https://github.com/deepset-ai/haystack-core-integrations/issues
Author-email: deepset GmbH <info@deepset.ai>
License-Expression: Apache-2.0
License-File: LICENSE.txt
Classifier: Development Status :: 4 - Beta
Classifier: License :: OSI Approved :: Apache Software License
Classifier: Programming Language :: Python
Classifier: Programming Language :: Python :: 3.9
Classifier: Programming Language :: Python :: 3.10
Classifier: Programming Language :: Python :: 3.11
Classifier: Programming Language :: Python :: 3.12
Classifier: Programming Language :: Python :: 3.13
Classifier: Programming Language :: Python :: Implementation :: CPython
Classifier: Programming Language :: Python :: Implementation :: PyPy
Requires-Python: >=3.9
Requires-Dist: haystack-ai>=2.12.0
